pyqtfork/__init__.py
pyqtfork/helpers.py
pyqtfork/utils.py
pyqtfork/widgets.py
pyqtfork-1.0.0.dist-info/LICENSE
pyqtfork-1.0.0.dist-info/METADATA
pyqtfork-1.0.0.dist-info/WHEEL
pyqtfork-1.0.0.dist-info/top_level.txt
pyqtfork-1.0.0.dist-info/RECORD
