Metadata-Version: 2.2
Name: Pyqtfork
Version: 1.0.0
Summary: Pyqtfork - Enhanced Python bindings for Qt
Home-page: https://github.com/pyqtfork/pyqtfork
Author: Pyqtfork Contributors
Author-email: info@pyqtfork.org
Project-URL: Documentation, https://pyqtfork.readthedocs.io/
Project-URL: Source, https://github.com/pyqtfork/pyqtfork
Project-URL: Tracker, https://github.com/pyqtfork/pyqtfork/issues
Keywords: qt gui pyqt pyqtfork ui interface fork
Classifier: Development Status :: 5 - Production/Stable
Classifier: Intended Audience :: Developers
Classifier: License :: OSI Approved :: GNU General Public License v3 (GPLv3)
Classifier: Programming Language :: Python
Classifier: Programming Language :: Python :: 3
Classifier: Programming Language :: Python :: 3.6
Classifier: Programming Language :: Python :: 3.7
Classifier: Programming Language :: Python :: 3.8
Classifier: Programming Language :: Python :: 3.9
Classifier: Programming Language :: Python :: 3.10
Classifier: Programming Language :: Python :: 3.11
Classifier: Topic :: Software Development :: User Interfaces
Classifier: Topic :: Software Development :: Libraries :: Python Modules
Requires-Python: >=3.6
License-File: LICENSE
Requires-Dist: PyQt5>=5.10.1
Dynamic: author
Dynamic: author-email
Dynamic: classifier
Dynamic: description
Dynamic: description-content-type
Dynamic: home-page
Dynamic: keywords
Dynamic: project-url
Dynamic: requires-dist
Dynamic: requires-python
Dynamic: summary
